PyColor/Colors.py
PyColor/Functions.py
PyColor/Palettes.py
PyColor/__init__.py
idev_pycolor-1.1.1.dist-info/LICENSE
idev_pycolor-1.1.1.dist-info/METADATA
idev_pycolor-1.1.1.dist-info/WHEEL
idev_pycolor-1.1.1.dist-info/top_level.txt
idev_pycolor-1.1.1.dist-info/RECORD
