Metadata-Version: 2.1
Name: idev-pycolor
Version: 1.1.1
Summary: A python collection of classes and functions to convert between multiple color models, generate palettes, and more.
Home-page: https://github.com/irtsa-dev/PyColor
Author: IrtsaDevelopment
Author-email: Irtsa <irtsa.development@gmail.com>
Project-URL: Homepage, https://github.com/irtsa-dev/PyColor
Project-URL: Bug Tracker, https://github.com/irtsa-dev/PyColor/issues
Classifier: Programming Language :: Python :: 3
Classifier: License :: OSI Approved :: MIT License
Classifier: Operating System :: OS Independent
Requires-Python: >=3.6
License-File: LICENSE
